CONTRIBUTORS.txt
LICENSE.txt
MANIFEST.in
README.rst
setup.py
cykooz/__init__.py
cykooz.recipe.patch.egg-info/PKG-INFO
cykooz.recipe.patch.egg-info/SOURCES.txt
cykooz.recipe.patch.egg-info/dependency_links.txt
cykooz.recipe.patch.egg-info/entry_points.txt
cykooz.recipe.patch.egg-info/namespace_packages.txt
cykooz.recipe.patch.egg-info/requires.txt
cykooz.recipe.patch.egg-info/top_level.txt
cykooz.recipe.patch.egg-info/zip-safe
cykooz/recipe/__init__.py
cykooz/recipe/patch/__init__.py
cykooz/recipe/patch/tests/__init__.py
cykooz/recipe/patch/tests/test_docs.py