Metadata-Version: 1.1
Name: cykooz.recipe.patch
Version: 0.1
Summary: recipe for patching eggs
Home-page: https://github.com/cykooz/cykooz.recipe.patch
Author: Kirill Kuzminykh
Author-email: saikuz@mail.ru
License: GPL
Keywords: buildout recipe patch
Platform: UNKNOWN
Classifier: Framework :: Buildout
Classifier: Intended Audience :: Developers
Classifier: Topic :: Software Development :: Build Tools
Classifier: Topic :: Software Development :: Libraries :: Python Modules
Classifier: License :: OSI Approved :: GNU General Public License (GPL)
